prompt4py/__init__.py
prompt4py/template/__init__.py
prompt4py/template/base_template.py
prompt4py/template/general_template.py
prompt4py/util/__init__.py
prompt4py/util/json2markdown.py
prompt4py-0.0.5.dist-info/licenses/LICENSE
prompt4py-0.0.5.dist-info/METADATA
prompt4py-0.0.5.dist-info/WHEEL
prompt4py-0.0.5.dist-info/top_level.txt
prompt4py-0.0.5.dist-info/RECORD
