Metadata-Version: 2.4
Name: prompt4py
Version: 0.0.5
Summary: Programmatic prompt template for Python.
Requires-Python: >=3.10
License-File: LICENSE
Requires-Dist: vortezwohl>=0.0.17
Dynamic: license-file
